modules/04-full_subtractor/full_subtractor_structural.v
`timescale 1ns/1ps
module full_subtractor_structural (
  input a,    // Input 'a'
  input b,    // Input 'b'
  input bin,  // Borrow-in 'bin'
  output diff,   // Output 'diff' (Difference)
  output bout // Output 'bout' (Borrow-out)
);

  xor gate_xor1 (diff1, a, b);          // XOR gate for first difference
  xor gate_xor2 (diff, diff1, bin);     // XOR gate for final difference
  and gate_and1 (and1, ~a, b);          // AND gate for first borrow-out term
  and gate_and2 (and2, ~a, bin);        // AND gate for second borrow-out term
  and gate_and3 (and3, b, bin);         // AND gate for third borrow-out term
  or gate_or (bout, and1, and2, and3);  // OR gate for final borrow-out

endmodule

modules/04-full_subtractor/full_subtractor_dataflow.v
`timescale 1ns/1ps
module full_subtractor_dataflow (
  input a,    // Input 'a'
  input b,    // Input 'b'
  input bin,  // Borrow-in 'bin'
  output diff,   // Output 'diff' (Difference)
  output bout // Output 'bout' (Borrow-out)
);

  assign diff = a ^ b ^ bin;     // Dataflow expression for difference
  assign bout = (~a & b) | (~a & bin) | (b & bin); // Dataflow expression for borrow-out

endmodule

modules/04-full_subtractor/full_subtractor_behavioral.v
`timescale 1ns/1ps
module full_subtractor_behavioral (
  input a,    // Input 'a'
  input b,    // Input 'b'
  input bin,  // Borrow-in 'bin'
  output reg diff,   // Output 'diff' (Difference)
  output reg bout // Output 'bout' (Borrow-out)
);

  // Combinational logic equations for difference and borrow-out
  always @(*) begin
    diff = a ^ b ^ bin;     // Difference
    bout = (~a & b) | (~a & bin) | (b & bin); // Borrow-out
  end

endmodule

modules/04-full_subtractor/full_subtractor_test_bench.v
`timescale 1ns/1ps
module full_subtractor_test_bench;

  // Declare registers
  reg a, b, bin;    // Registers for inputs
  
  // Declare wires
  wire d1, d2, d3;   // Wires for output 'diff' from different modules
  wire b1, b2, b3;   // Wires for output 'bout' from different modules
  
  // Instantiate full_subtractor_behavioral module
  full_subtractor_behavioral fs_behav (.a(a), .b(b), .bin(bin), .diff(d1), .bout(b1));
  
  // Instantiate full_subtractor_dataflow module
  full_subtractor_dataflow fs_data (.a(a), .b(b), .bin(bin), .diff(d2), .bout(b2));
  
  // Instantiate full_subtractor_structural module
  full_subtractor_structural fs_struct (.a(a), .b(b), .bin(bin), .diff(d3), .bout(b3));
  
  // Initial block for simulation
  initial begin
    $dumpvars(1, full_subtractor_test_bench); // Enable waveform dumping for simulation
    
    // Test case 1
    a = 1'b0; b = 1'b0; bin = 1'b0;   // Assign inputs
    #10;                             // Wait for 10 time units
    $display("Test case 1:");
    $display("Behavioral - diff=%b, bout=%b", d1, b1);
    $display("Dataflow - diff=%b, bout=%b", d2, b2);
    $display("Structural - diff=%b, bout=%b", d3, b3);
    
    // Test case 2
    a = 1'b0; b = 1'b1; bin = 1'b0;   // Assign inputs
    #10;                             // Wait for 10 time units
    $display("Test case 2:");
    $display("Behavioral - diff=%b, bout=%b", d1, b1);
    $display("Dataflow - diff=%b, bout=%b", d2, b2);
    $display("Structural - diff=%b, bout=%b", d3, b3);
    
    // Test case 3
    a = 1'b1; b = 1'b0; bin = 1'b0;   // Assign inputs
    #10;                             // Wait for 10 time units
    $display("Test case 3:");
    $display("Behavioral - diff=%b, bout=%b", d1, b1);
    $display("Dataflow - diff=%b, bout=%b", d2, b2);
    $display("Structural - diff=%b, bout=%b", d3, b3);
    
    // Test case 4
    a = 1'b1; b = 1'b1; bin = 1'b0;   // Assign inputs
    #10;                             // Wait for 10 time units
    $display("Test case 4:");
    $display("Behavioral - diff=%b, bout=%b", d1, b1);
    $display("Dataflow - diff=%b, bout=%b", d2, b2);
    $display("Structural - diff=%b, bout=%b", d3, b3);
    
    // Test case 5
    a = 1'b0; b = 1'b0; bin = 1'b1;   // Assign inputs
    #10;                             // Wait for 10 time units
    $display("Test case 5:");
    $display("Behavioral - diff=%b, bout=%b", d1, b1);
    $display("Dataflow - diff=%b, bout=%b", d2, b2);
    $display("Structural - diff=%b, bout=%b", d3, b3);
    
    // Test case 6
    a = 1'b0; b = 1'b1; bin = 1'b1;   // Assign inputs
    #10;                             // Wait for 10 time units
    $display("Test case 6:");
    $display("Behavioral - diff=%b, bout=%b", d1, b1);
    $display("Dataflow - diff=%b, bout=%b", d2, b2);
    $display("Structural - diff=%b, bout=%b", d3, b3);
    
    // Test case 7
    a = 1'b1; b = 1'b0; bin = 1'b1;   // Assign inputs
    #10;                             // Wait for 10 time units
    $display("Test case 7:");
    $display("Behavioral - diff=%b, bout=%b", d1, b1);
    $display("Dataflow - diff=%b, bout=%b", d2, b2);
    $display("Structural - diff=%b, bout=%b", d3, b3);
    
    // Test case 8
    a = 1'b1; b = 1'b1; bin = 1'b1;   // Assign inputs
    #10;                             // Wait for 10 time units
    $display("Test case 8:");
    $display("Behavioral - diff=%b, bout=%b", d1, b1);
    $display("Dataflow - diff=%b, bout=%b", d2, b2);
    $display("Structural - diff=%b, bout=%b", d3, b3);
    
    // End simulation
    $finish;
  end
endmodule

modules/04-full_subtractor/dump.vcd
$date
	Sat Jun 22 14:14:34 2024
$end
$version
	Icarus Verilog
$end
$timescale
	1ps
$end
$scope module full_subtractor_test_bench $end
$var wire 1 ! d3 $end
$var wire 1 " d2 $end
$var wire 1 # d1 $end
$var wire 1 $ b3 $end
$var wire 1 % b2 $end
$var wire 1 & b1 $end
$var reg 1 ' a $end
$var reg 1 ( b $end
$var reg 1 ) bin $end
$upscope $end
$enddefinitions $end
$comment Show the parameter values. $end
$dumpall
$end
#0
$dumpvars
0)
0(
0'
0&
0%
0$
0#
0"
0!
$end
#10000
1%
1"
1!
1$
1&
1#
1(
#20000
0%
0$
0&
0(
1'
#30000
0"
0!
0#
1(
#40000
1%
1$
1"
1!
1&
1#
1)
0(
0'
#50000
0"
0!
0#
1(
#60000
0%
0$
0&
0(
1'
#70000
1"
1%
1!
1$
1&
1#
1(
